dqbot/__init__.py
dqbot/__main__.py
dqbot/cli.py
dqbot/core.py
dqbot/vis_report.py
dqbot-0.1.4.dist-info/METADATA
dqbot-0.1.4.dist-info/WHEEL
dqbot-0.1.4.dist-info/entry_points.txt
dqbot-0.1.4.dist-info/top_level.txt
dqbot-0.1.4.dist-info/RECORD
