Metadata-Version: 2.4
Name: dqbot
Version: 0.1.4
Requires-Dist: pandas
Requires-Dist: numpy
Requires-Dist: matplotlib
Requires-Dist: seaborn
Requires-Dist: pyyaml
Requires-Dist: openpyxl
Requires-Dist: azure-storage-blob
Requires-Dist: argparse
Dynamic: requires-dist
